Metadata-Version: 2.1
Name: dolos
Version: 10.19.2
Summary: Python IB API
Home-page: 
Author: 
Author-email: 
License: UNKNOWN
Platform: UNKNOWN
License-File: LICENSE.txt
